bitbucket_hook_diffstat/__init__.py
bitbucket_hook_diffstat/exceptions.py
bitbucket_hook_diffstat/main.py
bitbucket_hook_diffstat-0.5.2.dist-info/WHEEL
bitbucket_hook_diffstat-0.5.2.dist-info/METADATA
bitbucket_hook_diffstat-0.5.2.dist-info/RECORD
