Metadata-Version: 2.1
Name: bitbucket-hook-diffstat
Version: 0.5.2
Summary: Bitbucket push webhook handler to generate a list of files changed on a push
Home-page: https://github.com/vavdoshka/bitbucket-hook-diffstat
Author: Vlad
Author-email: vova.avdoshka@gmail.com
Requires-Python: >=3.8,<4.0
Classifier: Programming Language :: Python :: 3
Classifier: Programming Language :: Python :: 3.8
Classifier: Programming Language :: Python :: 3.9
Requires-Dist: requests (>=2.28.1,<3.0.0)
Project-URL: Repository, https://github.com/vavdoshka/bitbucket-hook-diffstat
